[
    {
        "id": "目黒",
        "name": "目黒",
        "lines": [
            "目黒"
        ],
        "passengers": null,
        "firstDeparture": null,
        "lat": 35.6332,
        "lng": 139.71542
    },
    {
        "id": "白金台",
        "name": "白金台",
        "lines": [
            "白金台"
        ],
        "passengers": null,
        "firstDeparture": null,
        "lat": 35.63814,
        "lng": 139.72671
    },
    {
        "id": "白金高輪",
        "name": "白金高輪",
        "lines": [
            "白金高輪"
        ],
        "passengers": null,
        "firstDeparture": null,
        "lat": 35.64385,
        "lng": 139.73469
    },
    {
        "id": "麻布十番",
        "name": "麻布十番",
        "lines": [
            "麻布十番"
        ],
        "passengers": null,
        "firstDeparture": null,
        "lat": 35.65554,
        "lng": 139.73715
    },
    {
        "id": "六本木一丁目",
        "name": "六本木一丁目",
        "lines": [
            "六本木一丁目"
        ],
        "passengers": null,
        "firstDeparture": null,
        "lat": 35.66579,
        "lng": 139.73902
    },
    {
        "id": "溜池山王",
        "name": "溜池山王",
        "lines": [
            "溜池山王"
        ],
        "passengers": null,
        "firstDeparture": null,
        "lat": 35.67443,
        "lng": 139.74133
    },
    {
        "id": "永田町",
        "name": "永田町",
        "lines": [
            "永田町"
        ],
        "passengers": null,
        "firstDeparture": null,
        "lat": 35.67878,
        "lng": 139.73822
    },
    {
        "id": "四ツ谷",
        "name": "四ツ谷",
        "lines": [
            "四ツ谷"
        ],
        "passengers": null,
        "firstDeparture": null,
        "lat": 35.68712,
        "lng": 139.72999
    },
    {
        "id": "市ヶ谷",
        "name": "市ヶ谷",
        "lines": [
            "市ヶ谷"
        ],
        "passengers": null,
        "firstDeparture": null,
        "lat": 35.69417,
        "lng": 139.73766
    },
    {
        "id": "飯田橋",
        "name": "飯田橋",
        "lines": [
            "飯田橋"
        ],
        "passengers": null,
        "firstDeparture": null,
        "lat": 35.70262,
        "lng": 139.74454
    },
    {
        "id": "後楽園",
        "name": "後楽園",
        "lines": [
            "後楽園"
        ],
        "passengers": null,
        "firstDeparture": null,
        "lat": 35.70928,
        "lng": 139.7518
    },
    {
        "id": "東大前",
        "name": "東大前",
        "lines": [
            "東大前"
        ],
        "passengers": null,
        "firstDeparture": null,
        "lat": 35.71893,
        "lng": 139.7574
    },
    {
        "id": "本駒込",
        "name": "本駒込",
        "lines": [
            "本駒込"
        ],
        "passengers": null,
        "firstDeparture": null,
        "lat": 35.72517,
        "lng": 139.75366
    },
    {
        "id": "駒込",
        "name": "駒込",
        "lines": [
            "駒込"
        ],
        "passengers": null,
        "firstDeparture": null,
        "lat": 35.73648,
        "lng": 139.7466
    },
    {
        "id": "西ヶ原",
        "name": "西ヶ原",
        "lines": [
            "西ヶ原"
        ],
        "passengers": null,
        "firstDeparture": null,
        "lat": 35.74557,
        "lng": 139.74263
    },
    {
        "id": "王子",
        "name": "王子",
        "lines": [
            "王子"
        ],
        "passengers": null,
        "firstDeparture": null,
        "lat": 35.75355,
        "lng": 139.73779
    },
    {
        "id": "王子神谷",
        "name": "王子神谷",
        "lines": [
            "王子神谷"
        ],
        "passengers": null,
        "firstDeparture": null,
        "lat": 35.76418,
        "lng": 139.73597
    },
    {
        "id": "志茂",
        "name": "志茂",
        "lines": [
            "志茂"
        ],
        "passengers": null,
        "firstDeparture": null,
        "lat": 35.77728,
        "lng": 139.73303
    },
    {
        "id": "赤羽岩淵",
        "name": "赤羽岩淵",
        "lines": [
            "赤羽岩淵"
        ],
        "passengers": null,
        "firstDeparture": null,
        "lat": 35.7831,
        "lng": 139.72346
    },
    {
        "id": "南北線",
        "name": "南北線",
        "lines": [
            "南北線"
        ],
        "passengers": null,
        "firstDeparture": null,
        "lat": [
            139.7353,
            35.76654
        ],
        "lng": [
            139.73533,
            35.76641
        ]
    }
]